qolsys/actions.py
qolsys/config.py
qolsys/control.py
qolsys/events.py
qolsys/exceptions.py
qolsys/observable.py
qolsys/partition.py
qolsys/sensors.py
qolsys/socket.py
qolsys/state.py
qolsys/utils.py
qolsys-1.6.2.dist-info/METADATA
qolsys-1.6.2.dist-info/WHEEL
qolsys-1.6.2.dist-info/licenses/LICENSE
qolsys-1.6.2.dist-info/RECORD
