Metadata-Version: 2.4
Name: qolsys
Version: 1.6.2
Summary: Qolsys IQ Panel 2+ gateway API
Project-URL: Homepage, https://github.com/xaf/qolsysgw
Project-URL: Documentation, https://github.com/xaf/qolsysgw
Project-URL: Repository, https://github.com/xaf/qolsysgw.git
Project-URL: Issues, https://github.com/xaf/qolsysgw/issues
Project-URL: Changelog, https://github.com/xaf/qolsysgw/commits/main/
Author-email: Raphaël Beamonte <raphael.beamonte@gmail.com>
License: MIT License
License-File: LICENSE
Keywords: api,gateway,iq panel,qolsys
Classifier: Development Status :: 4 - Beta
Classifier: Intended Audience :: Developers
Classifier: License :: OSI Approved :: MIT License
Classifier: Programming Language :: Python :: 3
Requires-Python: >=3.8
